nep/__init__.py
nep/broker.py
nep/client.py
nep/helpers.py
nep/master.py
nep/node.py
nep/publisher.py
nep/server.py
nep/subscriber.py
nep-0.5.4.8.dist-info/LICENSE
nep-0.5.4.8.dist-info/METADATA
nep-0.5.4.8.dist-info/WHEEL
nep-0.5.4.8.dist-info/top_level.txt
nep-0.5.4.8.dist-info/RECORD
